drf_handlers/__init__.py
drf_handlers/__version__.py
drf_handlers/formatter.py
drf_errors_formatter-1.0.1.dist-info/LICENSE
drf_errors_formatter-1.0.1.dist-info/METADATA
drf_errors_formatter-1.0.1.dist-info/WHEEL
drf_errors_formatter-1.0.1.dist-info/top_level.txt
drf_errors_formatter-1.0.1.dist-info/RECORD
