Metadata-Version: 2.1
Name: drf-errors-formatter
Version: 1.0.1
Summary: Format errors in Django Rest Framework
Home-page: https://github.com/thomas545/drf-errors-formatter
Author: Thomas
Author-email: imichael@pm.me
License: MIT
Keywords: django rest errors format-errors api
Platform: UNKNOWN
Classifier: Framework :: Django
Classifier: Intended Audience :: Developers
Classifier: Intended Audience :: System Administrators
Classifier: Operating System :: OS Independent
Classifier: Topic :: Software Development
Requires-Python: >=3.6
License-File: LICENSE
Requires-Dist: Django (>=2.0)
Requires-Dist: djangorestframework (>=3.7.0)
